{
  "header": {
    "icon": {
      "color": "orange",
      "style": "float",
      "name": "tina"
    },
    "color": "default",
    "nav": [
      {
        "href": "",
        "label": "Home"
      },
      {
        "href": "about",
        "label": "About"
      },
      {
        "href": "posts",
        "label": "Blog"
      }
    ]
  },
  "footer": {
    "color": "default",
    "social": {
      "facebook": "/",
      "twitter": "/",
      "instagram": "/"
    }
  },
  "gtmId": "GTM-MS25MX2",
  "redirects": [
    {
      "from": "/ahs",
      "to": "/asia-hackathon-season"
    },
    {
      "from": "/asia-hackathon-site",
      "to": "/asia-hackathon-season"
    },
    {
      "from": "/dora-hacks",
      "to": "/dora-hacks-site"
    }
  ],
  "theme": {
    "color": "blue",
    "font": "sans",
    "icon": "boxicon",
    "darkMode": "system"
  }
}